{
  "id": "meet-the-team",
  "fields": [
    {
      "component": "text",
      "name": "sectionTitle",
      "label": "Section Title",
      "valueType": "string"
    },
    {
      "component": "text",
      "name": "teamTitle",
      "label": "Team Title",
      "valueType": "string"
    },
    {
      "component": "aem-content",
      "name": "teamImage1",
      "label": "Team Member 1 - Image"
    },
    {
      "component": "text",
      "name": "teamName1",
      "label": "Team Member 1 - Name",
      "valueType": "string"
    },
    {
      "component": "text",
      "name": "teamRole1",
      "label": "Team Member 1 - Role",
      "valueType": "string"
    },
    {
      "component": "aem-content",
      "name": "teamImage2",
      "label": "Team Member 2 - Image"
    },
    {
      "component": "text",
      "name": "teamName2",
      "label": "Team Member 2 - Name",
      "valueType": "string"
    },
    {
      "component": "text",
      "name": "teamRole2",
      "label": "Team Member 2 - Role",
      "valueType": "string"
    },
    {
      "component": "aem-content",
      "name": "teamImage3",
      "label": "Team Member 3 - Image"
    },
    {
      "component": "text",
      "name": "teamName3",
      "label": "Team Member 3 - Name",
      "valueType": "string"
    },
    {
      "component": "text",
      "name": "teamRole3",
      "label": "Team Member 3 - Role",
      "valueType": "string"
    },
    {
      "component": "aem-content",
      "name": "teamImage4",
      "label": "Team Member 4 - Image"
    },
    {
      "component": "text",
      "name": "teamName4",
      "label": "Team Member 4 - Name",
      "valueType": "string"
    },
    {
      "component": "text",
      "name": "teamRole4",
      "label": "Team Member 4 - Role",
      "valueType": "string"
    },
    {
      "component": "aem-content",
      "name": "teamImage5",
      "label": "Team Member 5 - Image"
    },
    {
      "component": "text",
      "name": "teamName5",
      "label": "Team Member 5 - Name",
      "valueType": "string"
    },
    {
      "component": "text",
      "name": "teamRole5",
      "label": "Team Member 5 - Role",
      "valueType": "string"
    },
    {
      "component": "aem-content",
      "name": "teamImage6",
      "label": "Team Member 6 - Image"
    },
    {
      "component": "text",
      "name": "teamName6",
      "label": "Team Member 6 - Name",
      "valueType": "string"
    },
    {
      "component": "text",
      "name": "teamRole6",
      "label": "Team Member 6 - Role",
      "valueType": "string"
    },
    {
      "component": "text",
      "name": "aboutTitle",
      "label": "About Section Title",
      "valueType": "string"
    },
    {
      "component": "richtext",
      "name": "aboutDescription",
      "label": "About Description",
      "valueType": "string"
    },
    {
      "component": "aem-content",
      "name": "cta1Link",
      "label": "CTA Button Link"
    },
    {
      "component": "text",
      "name": "cta1LinkText",
      "label": "CTA Button Text",
      "valueType": "string"
    },
    {
      "component": "select",
      "name": "cta1Variant",
      "label": "CTA Button Style",
      "valueType": "string",
      "options": [
        {
          "name": "Purple",
          "value": "[variant-purple]"
        },
        {
          "name": "Black",
          "value": "[variant-black]"
        },
        {
          "name": "White Outline",
          "value": "[variant-white-outline]"
        },
        {
          "name": "White",
          "value": "[variant-white]"
        },
        {
          "name": "Outline",
          "value": "[variant-outline]"
        },
        {
          "name": "White Outline Medium",
          "value": "[variant-white-outline-medium]"
        },
        {
          "name": "Orange Underline",
          "value": "[variant-orange-underline]"
        },
        {
          "name": "Nuevo",
          "value": "[variant-nuevo]"
        },
        {
          "name": "Gray",
          "value": "[variant-gray]"
        }
      ]
    }
  ]
}